pton_pgk/__init__.py
pton_pgk-0.1.2.dist-info/WHEEL
pton_pgk-0.1.2.dist-info/METADATA
pton_pgk-0.1.2.dist-info/RECORD
