Metadata-Version: 2.1
Name: pton-pgk
Version: 0.1.2
Summary: Medieval City
Author: Tom
Author-email: tom.thil@epita.fr
Requires-Python: >=3.8,<4.0
Classifier: Programming Language :: Python :: 3
Classifier: Programming Language :: Python :: 3.8
Classifier: Programming Language :: Python :: 3.9
Requires-Dist: Shapely (>=1.7.1,<2.0.0)
Requires-Dist: geopandas (>=0.9.0,<0.10.0)
Requires-Dist: numpy (>=1.21.0,<2.0.0)
